{
  "_schema": "manifest/v1",
  "_updated": "2026-04-11",
  "empresa": "cury",
  "display_name": "Cury Construtora e Incorporadora S.A.",
  "aliases": [
    "Cury",
    "CURY3"
  ],
  "ticker": "CURY3",
  "setor": "incorporadora",
  "setor_schema": "sources/structured/_schemas/incorporadora.json",
  "wiki_page": "cury.md",
  "sources": [
    {
      "type": "release",
      "asof": "1T23",
      "ingested_on": "2026-04-11",
      "full": "sources/full/cury/1T23/release.md",
      "structured": [
        "sources/structured/cury/1T23/release.json"
      ],
      "digested": "sources/digested/cury_release_1T23_summary.md"
    },
    {
      "type": "release",
      "asof": "1T24",
      "ingested_on": "2026-04-11",
      "full": "sources/full/cury/1T24/release.md",
      "structured": [
        "sources/structured/cury/1T24/release.json"
      ],
      "digested": "sources/digested/cury_release_1T24_summary.md"
    },
    {
      "type": "release",
      "asof": "1T25",
      "ingested_on": "2026-04-11",
      "full": "sources/full/cury/1T25/release.md",
      "structured": [
        "sources/structured/cury/1T25/release.json"
      ],
      "digested": "sources/digested/cury_release_1T25_summary.md"
    },
    {
      "type": "release",
      "asof": "2T23",
      "ingested_on": "2026-04-11",
      "full": "sources/full/cury/2T23/release.md",
      "structured": [
        "sources/structured/cury/2T23/release.json"
      ],
      "digested": "sources/digested/cury_release_2T23_summary.md"
    },
    {
      "type": "release",
      "asof": "2T24",
      "ingested_on": "2026-04-11",
      "full": "sources/full/cury/2T24/release.md",
      "structured": [
        "sources/structured/cury/2T24/release.json"
      ],
      "digested": "sources/digested/cury_release_2T24_summary.md"
    },
    {
      "type": "release",
      "asof": "2T25",
      "ingested_on": "2026-04-11",
      "full": "sources/full/cury/2T25/release.md",
      "structured": [
        "sources/structured/cury/2T25/release.json"
      ],
      "digested": "sources/digested/cury_release_2T25_summary.md"
    },
    {
      "type": "release",
      "asof": "3T23",
      "ingested_on": "2026-04-11",
      "full": "sources/full/cury/3T23/release.md",
      "structured": [
        "sources/structured/cury/3T23/release.json"
      ],
      "digested": "sources/digested/cury_release_3T23_summary.md"
    },
    {
      "type": "release",
      "asof": "3T24",
      "ingested_on": "2026-04-11",
      "full": "sources/full/cury/3T24/release.md",
      "structured": [
        "sources/structured/cury/3T24/release.json"
      ],
      "digested": "sources/digested/cury_release_3T24_summary.md"
    },
    {
      "type": "release",
      "asof": "3T25",
      "ingested_on": "2026-04-11",
      "full": "sources/full/cury/3T25/release.md",
      "structured": [
        "sources/structured/cury/3T25/release.json"
      ],
      "digested": "sources/digested/cury_release_3T25_summary.md"
    },
    {
      "type": "release",
      "asof": "4T22",
      "ingested_on": "2026-04-11",
      "full": "sources/full/cury/4T22/release.md",
      "structured": [
        "sources/structured/cury/4T22/release.json"
      ],
      "digested": "sources/digested/cury_release_4T22_summary.md"
    },
    {
      "type": "release",
      "asof": "4T23",
      "ingested_on": "2026-04-11",
      "full": "sources/full/cury/4T23/release.md",
      "structured": [
        "sources/structured/cury/4T23/release.json"
      ],
      "digested": "sources/digested/cury_release_4T23_summary.md"
    },
    {
      "type": "release",
      "asof": "4T24",
      "ingested_on": "2026-04-11",
      "full": "sources/full/cury/4T24/release.md",
      "structured": [
        "sources/structured/cury/4T24/release.json"
      ],
      "digested": "sources/digested/cury_release_4T24_summary.md"
    },
    {
      "type": "release",
      "asof": "4T25",
      "ingested_on": "2026-04-11",
      "full": "sources/full/cury/4T25/release.md",
      "structured": [
        "sources/structured/cury/4T25/release.json"
      ],
      "digested": "sources/digested/cury_release_4T25_summary.md"
    },
    {
      "type": "fato_relevante",
      "asof": "1T26",
      "ingested_on": "2026-04-11",
      "full": "sources/full/cury/1T26/fato_relevante_1015615.md",
      "digested": "sources/digested/cury_fatos_relevantes_batch_summary.md"
    },
    {
      "type": "fato_relevante",
      "asof": "2T25",
      "ingested_on": "2026-04-11",
      "full": "sources/full/cury/2T25/fato_relevante_889685.md",
      "digested": "sources/digested/cury_fatos_relevantes_batch_summary.md"
    },
    {
      "type": "fato_relevante",
      "asof": "3T25",
      "ingested_on": "2026-04-11",
      "full": "sources/full/cury/3T25/fato_relevante_932870.md",
      "digested": "sources/digested/cury_fatos_relevantes_batch_summary.md"
    },
    {
      "type": "fato_relevante",
      "asof": "4T24",
      "ingested_on": "2026-04-11",
      "full": "sources/full/cury/4T24/fato_relevante_841950.md",
      "digested": "sources/digested/cury_fatos_relevantes_batch_summary.md"
    },
    {
      "type": "fato_relevante",
      "asof": "4T25",
      "ingested_on": "2026-04-11",
      "full": "sources/full/cury/4T25/fato_relevante_977461.md",
      "digested": "sources/digested/cury_fatos_relevantes_batch_summary.md"
    },
    {
      "type": "fato_relevante",
      "asof": "4T25",
      "ingested_on": "2026-04-11",
      "full": "sources/full/cury/4T25/fato_relevante_981184.md",
      "digested": "sources/digested/cury_fatos_relevantes_batch_summary.md"
    },
    {
      "type": "release",
      "asof": "unknown",
      "ingested_on": "2026-04-11",
      "full": "sources/full/cury/other/CURY3_1T23_itr_126022.md",
      "digested": "sources/digested/cury_other_CURY3_1T23_itr_126022_summary.md"
    },
    {
      "type": "release",
      "asof": "unknown",
      "ingested_on": "2026-04-11",
      "full": "sources/full/cury/other/CURY3_1T24_itr_136591.md",
      "digested": "sources/digested/cury_other_CURY3_1T24_itr_136591_summary.md"
    },
    {
      "type": "release",
      "asof": "unknown",
      "ingested_on": "2026-04-11",
      "full": "sources/full/cury/other/CURY3_1T25_itr_147489.md",
      "digested": "sources/digested/cury_other_CURY3_1T25_itr_147489_summary.md"
    },
    {
      "type": "release",
      "asof": "unknown",
      "ingested_on": "2026-04-11",
      "full": "sources/full/cury/other/CURY3_2022_dfp_130992.md",
      "digested": "sources/digested/cury_other_CURY3_2022_dfp_130992_summary.md"
    },
    {
      "type": "release",
      "asof": "unknown",
      "ingested_on": "2026-04-11",
      "full": "sources/full/cury/other/CURY3_2023_dfp_134624.md",
      "digested": "sources/digested/cury_other_CURY3_2023_dfp_134624_summary.md"
    },
    {
      "type": "release",
      "asof": "unknown",
      "ingested_on": "2026-04-11",
      "full": "sources/full/cury/other/CURY3_2024_dfp_145292.md",
      "digested": "sources/digested/cury_other_CURY3_2024_dfp_145292_summary.md"
    },
    {
      "type": "release",
      "asof": "unknown",
      "ingested_on": "2026-04-11",
      "full": "sources/full/cury/other/CURY3_2025_dfp_155237.md",
      "digested": "sources/digested/cury_other_CURY3_2025_dfp_155237_summary.md"
    },
    {
      "type": "release",
      "asof": "unknown",
      "ingested_on": "2026-04-11",
      "full": "sources/full/cury/other/CURY3_2T23_itr_129820.md",
      "digested": "sources/digested/cury_other_CURY3_2T23_itr_129820_summary.md"
    },
    {
      "type": "release",
      "asof": "unknown",
      "ingested_on": "2026-04-11",
      "full": "sources/full/cury/other/CURY3_2T24_itr_140423.md",
      "digested": "sources/digested/cury_other_CURY3_2T24_itr_140423_summary.md"
    },
    {
      "type": "release",
      "asof": "unknown",
      "ingested_on": "2026-04-11",
      "full": "sources/full/cury/other/CURY3_2T25_itr_150599.md",
      "digested": "sources/digested/cury_other_CURY3_2T25_itr_150599_summary.md"
    },
    {
      "type": "release",
      "asof": "unknown",
      "ingested_on": "2026-04-11",
      "full": "sources/full/cury/other/CURY3_3T23_itr_131846.md",
      "digested": "sources/digested/cury_other_CURY3_3T23_itr_131846_summary.md"
    },
    {
      "type": "release",
      "asof": "unknown",
      "ingested_on": "2026-04-11",
      "full": "sources/full/cury/other/CURY3_3T24_itr_142960.md",
      "digested": "sources/digested/cury_other_CURY3_3T24_itr_142960_summary.md"
    },
    {
      "type": "release",
      "asof": "unknown",
      "ingested_on": "2026-04-11",
      "full": "sources/full/cury/other/CURY3_3T25_itr_152937.md",
      "digested": "sources/digested/cury_other_CURY3_3T25_itr_152937_summary.md"
    }
  ],
  "coverage": {
    "1T23": {
      "financeiro_ajustado": {
        "status": "filled",
        "source": "sources/structured/cury/1T23/release.json"
      }
    },
    "1T24": {
      "financeiro_ajustado": {
        "status": "filled",
        "source": "sources/structured/cury/1T24/release.json"
      }
    },
    "1T25": {
      "financeiro_ajustado": {
        "status": "filled",
        "source": "sources/structured/cury/1T25/release.json"
      }
    },
    "2T23": {
      "financeiro_ajustado": {
        "status": "filled",
        "source": "sources/structured/cury/2T23/release.json"
      }
    },
    "2T24": {
      "financeiro_ajustado": {
        "status": "filled",
        "source": "sources/structured/cury/2T24/release.json"
      }
    },
    "2T25": {
      "financeiro_ajustado": {
        "status": "filled",
        "source": "sources/structured/cury/2T25/release.json"
      }
    },
    "3T23": {
      "financeiro_ajustado": {
        "status": "filled",
        "source": "sources/structured/cury/3T23/release.json"
      }
    },
    "3T24": {
      "financeiro_ajustado": {
        "status": "filled",
        "source": "sources/structured/cury/3T24/release.json"
      }
    },
    "3T25": {
      "financeiro_ajustado": {
        "status": "filled",
        "source": "sources/structured/cury/3T25/release.json"
      }
    },
    "4T22": {
      "financeiro_ajustado": {
        "status": "filled",
        "source": "sources/structured/cury/4T22/release.json"
      }
    },
    "4T23": {
      "financeiro_ajustado": {
        "status": "filled",
        "source": "sources/structured/cury/4T23/release.json"
      }
    },
    "4T24": {
      "financeiro_ajustado": {
        "status": "filled",
        "source": "sources/structured/cury/4T24/release.json"
      }
    },
    "4T25": {
      "financeiro_ajustado": {
        "status": "filled",
        "source": "sources/structured/cury/4T25/release.json"
      }
    }
  },
  "precedence": [],
  "caveats": [
    "cold-start — manifest criado por fetch agent, pendente ingest"
  ],
  "fetch_profile": {
    "_created": "2026-04-11",
    "_sample_period": "4T25",
    "categories": {
      "release_resultado_pt": {
        "action": "include",
        "description": "Release de resultados trimestral/anual em portugues",
        "sample_files": [
          "CURY3_4T25_release_1013143.pdf"
        ]
      },
      "demonstracoes_financeiras": {
        "action": "include",
        "description": "DFP/ITR completo com relatorio do auditor (classificado pela CVM como release)",
        "sample_files": [
          "CURY3_4T25_release_1013149.pdf"
        ]
      },
      "fato_relevante_oferta": {
        "action": "include",
        "description": "Fatos relevantes sobre oferta primaria de acoes (registro, pricing)",
        "sample_files": [
          "CURY3_4T25_fato_relevante_977461.pdf",
          "CURY3_4T25_fato_relevante_981184.pdf"
        ]
      }
    }
  },
  "related_digests": []
}
